{"nodes": [{"id": "itsm_frontend_src_app_main_enterprise_teams_page_tsx", "label": "page.tsx", "file_type": "code", "source_file": "itsm-frontend/src/app/(main)/enterprise/teams/page.tsx", "source_location": "L1"}, {"id": "page_fetchusers", "label": "fetchUsers()", "file_type": "code", "source_file": "itsm-frontend/src/app/(main)/enterprise/teams/page.tsx", "source_location": "L39"}, {"id": "page_fetchteams", "label": "fetchTeams()", "file_type": "code", "source_file": "itsm-frontend/src/app/(main)/enterprise/teams/page.tsx", "source_location": "L53"}, {"id": "page_catch", "label": "catch()", "file_type": "code", "source_file": "itsm-frontend/src/app/(main)/enterprise/teams/page.tsx", "source_location": "L162"}], "edges": [{"source": "itsm_frontend_src_app_main_enterprise_teams_page_tsx", "target": "react", "relation": "imports_from", "confidence": "EXTRACTED", "source_file": "itsm-frontend/src/app/(main)/enterprise/teams/page.tsx", "source_location": "L3", "weight": 1.0}, {"source": "itsm_frontend_src_app_main_enterprise_teams_page_tsx", "target": "antd", "relation": "imports_from", "confidence": "EXTRACTED", "source_file": "itsm-frontend/src/app/(main)/enterprise/teams/page.tsx", "source_location": "L4", "weight": 1.0}, {"source": "itsm_frontend_src_app_main_enterprise_teams_page_tsx", "target": "icons", "relation": "imports_from", "confidence": "EXTRACTED", "source_file": "itsm-frontend/src/app/(main)/enterprise/teams/page.tsx", "source_location": "L17", "weight": 1.0}, {"source": "itsm_frontend_src_app_main_enterprise_teams_page_tsx", "target": "pagecontainer", "relation": "imports_from", "confidence": "EXTRACTED", "source_file": "itsm-frontend/src/app/(main)/enterprise/teams/page.tsx", "source_location": "L24", "weight": 1.0}, {"source": "itsm_frontend_src_app_main_enterprise_teams_page_tsx", "target": "team_service", "relation": "imports_from", "confidence": "EXTRACTED", "source_file": "itsm-frontend/src/app/(main)/enterprise/teams/page.tsx", "source_location": "L25", "weight": 1.0}, {"source": "itsm_frontend_src_app_main_enterprise_teams_page_tsx", "target": "user_api", "relation": "imports_from", "confidence": "EXTRACTED", "source_file": "itsm-frontend/src/app/(main)/enterprise/teams/page.tsx", "source_location": "L27", "weight": 1.0}, {"source": "itsm_frontend_src_app_main_enterprise_teams_page_tsx", "target": "i18n", "relation": "imports_from", "confidence": "EXTRACTED", "source_file": "itsm-frontend/src/app/(main)/enterprise/teams/page.tsx", "source_location": "L28", "weight": 1.0}, {"source": "itsm_frontend_src_app_main_enterprise_teams_page_tsx", "target": "page_fetchusers", "relation": "contains", "confidence": "EXTRACTED", "source_file": "itsm-frontend/src/app/(main)/enterprise/teams/page.tsx", "source_location": "L39", "weight": 1.0}, {"source": "itsm_frontend_src_app_main_enterprise_teams_page_tsx", "target": "page_fetchteams", "relation": "contains", "confidence": "EXTRACTED", "source_file": "itsm-frontend/src/app/(main)/enterprise/teams/page.tsx", "source_location": "L53", "weight": 1.0}, {"source": "itsm_frontend_src_app_main_enterprise_teams_page_tsx", "target": "page_catch", "relation": "contains", "confidence": "EXTRACTED", "source_file": "itsm-frontend/src/app/(main)/enterprise/teams/page.tsx", "source_location": "L162", "weight": 1.0}], "raw_calls": [{"caller_nid": "page_fetchusers", "callee": "getUsers", "source_file": "itsm-frontend/src/app/(main)/enterprise/teams/page.tsx", "source_location": "L41"}, {"caller_nid": "page_fetchusers", "callee": "setUsers", "source_file": "itsm-frontend/src/app/(main)/enterprise/teams/page.tsx", "source_location": "L42"}, {"caller_nid": "page_fetchusers", "callee": "map", "source_file": "itsm-frontend/src/app/(main)/enterprise/teams/page.tsx", "source_location": "L43"}, {"caller_nid": "page_fetchusers", "callee": "error", "source_file": "itsm-frontend/src/app/(main)/enterprise/teams/page.tsx", "source_location": "L49"}, {"caller_nid": "page_fetchteams", "callee": "setFetching", "source_file": "itsm-frontend/src/app/(main)/enterprise/teams/page.tsx", "source_location": "L54"}, {"caller_nid": "page_fetchteams", "callee": "listTeams", "source_file": "itsm-frontend/src/app/(main)/enterprise/teams/page.tsx", "source_location": "L56"}, {"caller_nid": "page_fetchteams", "callee": "setTeams", "source_file": "itsm-frontend/src/app/(main)/enterprise/teams/page.tsx", "source_location": "L57"}, {"caller_nid": "page_fetchteams", "callee": "error", "source_file": "itsm-frontend/src/app/(main)/enterprise/teams/page.tsx", "source_location": "L59"}, {"caller_nid": "page_fetchteams", "callee": "error", "source_file": "itsm-frontend/src/app/(main)/enterprise/teams/page.tsx", "source_location": "L60"}, {"caller_nid": "page_fetchteams", "callee": "t", "source_file": "itsm-frontend/src/app/(main)/enterprise/teams/page.tsx", "source_location": "L60"}, {"caller_nid": "page_fetchteams", "callee": "setFetching", "source_file": "itsm-frontend/src/app/(main)/enterprise/teams/page.tsx", "source_location": "L62"}, {"caller_nid": "page_catch", "callee": "error", "source_file": "itsm-frontend/src/app/(main)/enterprise/teams/page.tsx", "source_location": "L163"}, {"caller_nid": "page_catch", "callee": "error", "source_file": "itsm-frontend/src/app/(main)/enterprise/teams/page.tsx", "source_location": "L164"}, {"caller_nid": "page_catch", "callee": "t", "source_file": "itsm-frontend/src/app/(main)/enterprise/teams/page.tsx", "source_location": "L164"}]}